skeletone/__init__.py
skeletone/cli.py
skeletone/downgrade.py
skeletone/help.py
skeletone/init.py
skeletone/patches.py
skeletone/upgrade.py
skeletone/versions.py
skeletone-0.1.14.dist-info/licenses/LICENSE
skeletone-0.1.14.dist-info/METADATA
skeletone-0.1.14.dist-info/WHEEL
skeletone-0.1.14.dist-info/entry_points.txt
skeletone-0.1.14.dist-info/top_level.txt
skeletone-0.1.14.dist-info/RECORD
