Metadata-Version: 2.4
Name: skeletone
Version: 0.1.14
Summary: CLI for services template for Python (FastAPI, SQLAlchemy, Alembic)
Author-email: Zhaxybayev Daulet <damelimm@gmail.com>
License: MIT
License-File: LICENSE
Requires-Dist: click
Requires-Dist: GitPython
Requires-Dist: rich
Requires-Dist: requests
Dynamic: license-file
